MANIFEST.in
README.rst
setup.cfg
setup.py
jicgeometry/__init__.py
jicgeometry.egg-info/PKG-INFO
jicgeometry.egg-info/SOURCES.txt
jicgeometry.egg-info/dependency_links.txt
jicgeometry.egg-info/top_level.txt