Metadata-Version: 1.1
Name: jicgeometry
Version: 0.6.0
Summary: Basic Python geometry package with no external dependencies.
Home-page: https://github.com/JIC-CSB/jicgeometry
Author: Tjelvar Olsson
Author-email: tjelvar.olsson@jic.ac.uk
License: MIT
Download-URL: https://github.com/JIC-CSB/jicgeometry/tarball/0.6.0
Keywords: geometry
Platform: UNKNOWN
Classifier: Development Status :: 3 - Alpha
Classifier: Intended Audience :: Developers
Classifier: Intended Audience :: Science/Research
Classifier: License :: OSI Approved :: MIT License
Classifier: Natural Language :: English
Classifier: Programming Language :: Python
Classifier: Programming Language :: Python :: 2
Classifier: Programming Language :: Python :: 2.7
Classifier: Topic :: Scientific/Engineering
